mkdocs_toc_sidebar_plugin/__init__.py
mkdocs_toc_sidebar_plugin/plugin.py
mkdocs_toc_sidebar_plugin-0.1.0.dist-info/LICENSE
mkdocs_toc_sidebar_plugin-0.1.0.dist-info/METADATA
mkdocs_toc_sidebar_plugin-0.1.0.dist-info/WHEEL
mkdocs_toc_sidebar_plugin-0.1.0.dist-info/entry_points.txt
mkdocs_toc_sidebar_plugin-0.1.0.dist-info/top_level.txt
mkdocs_toc_sidebar_plugin-0.1.0.dist-info/RECORD
